tks_simple_pika_consumer.py
tks_simple_pika_publisher.py
tks_simple_pika-1.1.8.dist-info/METADATA
tks_simple_pika-1.1.8.dist-info/WHEEL
tks_simple_pika-1.1.8.dist-info/top_level.txt
tks_simple_pika-1.1.8.dist-info/RECORD
