Metadata-Version: 2.1
Name: tks-simple-pika
Version: 1.1.8
Summary: Library for a simple implementation of a RabbitMQ consumer and producer using the python pika library
Home-page: 
Author: Oscar Fernandez Robles
Author-email: oskijob@gmail.com
License: MIT
Requires-Dist: pika
Requires-Dist: pydantic
Requires-Dist: pydantic[email]
Requires-Dist: python-decouple
